examples/basic_usage.py
persian_logger/__init__.py
persian_logger/__version__.py
persian_logger/converter.py
persian_logger/formatter.py
persian_logger/logger.py
persian_logger/terminal_supports_rtl.py
tests/__init__.py
tests/test_console_formatter.py
tests/test_file_formatter.py
tests/test_loggger_core.py
tests/test_terminal_detection.py
persian_logger-1.0.0.dist-info/METADATA
persian_logger-1.0.0.dist-info/WHEEL
persian_logger-1.0.0.dist-info/top_level.txt
persian_logger-1.0.0.dist-info/RECORD
