Metadata-Version: 2.4
Name: persian-logger
Version: 1.0.0
Summary: لاگ‌گیری فارسی با RTL، تاریخ جلالی و سطوح فارسی
Author-email: نام شما <you@example.com>
License: MIT
Project-URL: Source, https://github.com/yourname/persian-logger
Keywords: persian,farsi,logging,rtl,jalali
Classifier: Programming Language :: Python :: 3
Classifier: License :: OSI Approved :: MIT License
Classifier: Natural Language :: Persian
Requires-Python: >=3.8
Requires-Dist: arabic-reshaper==3.0.0
Requires-Dist: iniconfig==2.3.0
Requires-Dist: jalali_core==1.0.0
Requires-Dist: jdatetime==5.2.0
Requires-Dist: packaging==25.0
Requires-Dist: pluggy==1.6.0
Requires-Dist: Pygments==2.19.2
Requires-Dist: pytest==8.4.2
Requires-Dist: python-bidi==0.6.7
